dokku_wrapper/__init__.py
dokku_wrapper/dokku.py
dokku_wrapper/core/__init__.py
dokku_wrapper/core/exceptions.py
dokku_wrapper/core/executor.py
dokku_wrapper/core/parser.py
dokku_wrapper/core/types.py
dokku_wrapper/models/__init__.py
dokku_wrapper/models/app.py
dokku_wrapper/services/__init__.py
dokku_wrapper/services/apps.py
dokku_wrapper-0.1.4.dist-info/licenses/LICENSE
dokku_wrapper-0.1.4.dist-info/METADATA
dokku_wrapper-0.1.4.dist-info/WHEEL
dokku_wrapper-0.1.4.dist-info/top_level.txt
dokku_wrapper-0.1.4.dist-info/RECORD
